alarmdealerscrape.py
alarmdealerscrape-1.0.3.dist-info/LICENSE
alarmdealerscrape-1.0.3.dist-info/METADATA
alarmdealerscrape-1.0.3.dist-info/WHEEL
alarmdealerscrape-1.0.3.dist-info/top_level.txt
alarmdealerscrape-1.0.3.dist-info/RECORD
