Metadata-Version: 2.1
Name: alarmdealerscrape
Version: 1.0.3
Summary: scraper for alarmdealer.com
Home-page: https://github.com/tubaman/alarmdealerscrape
Author: Ryan Nowakowski
Author-email: tubaman@fattuba.com
License: BSD
Platform: UNKNOWN
Classifier: Intended Audience :: Developers
Classifier: License :: OSI Approved :: BSD License
Classifier: Programming Language :: Python
Classifier: Programming Language :: Python :: 2
Classifier: Programming Language :: Python :: 3
Classifier: Operating System :: OS Independent
Classifier: Topic :: Home Automation
Classifier: Topic :: Software Development :: Libraries
Requires-Dist: beautifulsoup4 (==4.7.1)
Requires-Dist: requests (==2.21.0)
Requires-Dist: websocket-client (==0.54.0)
